{"registry":{"namespace":"mason-org","proto":"github","version":"2026-04-04-baby-peace","name":"mason-registry","checksums":{"registry.json":"807e2257b96b89571a58ba8d9bcf68613861cd34e7fb8fc78e694a1134715167","registry.json.zip":"454dd13feefe5a1647681bc52fbc73e0f3864d177952245c74e73262cd3b089e"}},"links":{"opt":{},"bin":{"goimports":"goimports"},"share":{}},"install_options":{"strict":false,"force":false,"debug":false},"metrics":{"completion_time":1775284217978,"start_time":1775284215485},"name":"goimports","source":{"type":"registry+v1","id":"pkg:golang/golang.org/x/tools@v0.43.0#cmd/goimports","raw":{"id":"pkg:golang/golang.org/x/tools@v0.43.0#cmd/goimports"}},"schema_version":"2.0"}